{
"type": "FeatureCollection",
"name": "PawiSighting",
"crs": { "type": "name", "properties": { "name": "urn:ogc:def:crs:OGC:1.3:CRS84" } },
"features": [
{ "type": "Feature", "properties": { "X": 687619.2, "Y": 1185239.9, "Location": "Morne Bleu", "Sightings": "Confirmed" }, "geometry": { "type": "Point", "coordinates": [ -61.284419689855618, 10.717263678638387 ] } }
]
}
